{"type":"FeatureCollection","features":[{"type": "Feature", "id": "55EcD-GBhxTcaWOwRgWVsUW_czA=", "properties": {"ref": "/fr/fr/home/a-propos-de-kpmg/offices/saint-malo-cedex.html", "@spider": "kpmg_fr", "office": "consulting", "addr:full": "25 rue Arkansas", "addr:city": "Saint-Malo", "addr:postcode": "35400", "addr:country": "FR", "name": "Bureau KPMG Saint-Malo", "phone": "+33 (0)2 23 18 00 35", "website": "https://home.kpmg/fr/fr/home/a-propos-de-kpmg/offices/saint-malo-cedex.html", "brand": "KPMG", "brand:wikidata": "Q493751", "nsi_id": "kpmg-2207a5"}, "geometry": {"type": "Point", "coordinates": [-1.990467, 48.637956]}},
{"type": "Feature", "id": "mAbwssDT9bx9CqIW8QxxoMasP58=", "properties": {"ref": "/fr/fr/home/a-propos-de-kpmg/offices/paris-rue-du-faubourg-saint-antoine.html", "@spider": "kpmg_fr", "office": "consulting", "addr:full": "5 rue du Faubourg Saint-Antoine", "addr:city": "Paris", "addr:postcode": "75011", "addr:country": "FR", "name": "Bureau KPMG Paris \u2013 rue du Faubourg Saint-Antoine", "phone": "+33 (0)1 56 95 46 80", "website": "https://home.kpmg/fr/fr/home/a-propos-de-kpmg/offices/paris-rue-du-faubourg-saint-antoine.html", "brand": "KPMG", "brand:wikidata": "Q493751", "nsi_id": "kpmg-2207a5"}, "geometry": {"type": "Point", "coordinates": [2.371217, 48.853124]}},
{"type": "Feature", "id": "gbZexxx1THxtChbp7wuD7Uj-WgY=", "properties": {"ref": "/fr/fr/home/a-propos-de-kpmg/offices/morteau-cedex-111.html", "@spider": "kpmg_fr", "office": "consulting", "addr:full": "8 avenue Charles de Gaulle", "addr:city": "Morteau", "addr:postcode": "25503", "addr:country": "FR", "name": "Bureau KPMG Morteau", "phone": "+33 (0)3 81 67 19 23", "website": "https://home.kpmg/fr/fr/home/a-propos-de-kpmg/offices/morteau-cedex-111.html", "brand": "KPMG", "brand:wikidata": "Q493751", "nsi_id": "kpmg-2207a5"}, "geometry": {"type": "Point", "coordinates": [6.612248, 47.056835]}}]}